hypmix/__init__.py
hypmix/endmember.py
hypmix/file_opening_utils.py
hypmix/helper_functions.py
hypmix/io.py
hypmix/main.py
hypmix/mixview/__init__.py
hypmix/mixview/catalog/__init__.py
hypmix/mixview/catalog/actions.py
hypmix/mixview/catalog/handlers.py
hypmix/mixview/endmember_viewer.py
hypmix/mixview/image_view_container.py
hypmix/mixview/main_window.py
hypmix/mixview/model_tree.py
hypmix/mixview/model_viewer.py
hypmix/model_math.py
hypmix/py.typed
hypmix/resources/images/gui_example.png
hypmix/run_model.py
hypmix/typing.py
hypmix/util_classes.py
hypmix-0.2.4.dist-info/entry_points.txt
hypmix-0.2.4.dist-info/licenses/LICENSE
hypmix-0.2.4.dist-info/METADATA
hypmix-0.2.4.dist-info/WHEEL
hypmix-0.2.4.dist-info/RECORD
